django_cad_inspector/__init__.py
django_cad_inspector/admin.py
django_cad_inspector/apps.py
django_cad_inspector/models.py
django_cad_inspector/urls.py
django_cad_inspector/views.py
django_cad_inspector/migrations/0001_initial.py
django_cad_inspector/migrations/0002_materialimage.py
django_cad_inspector/migrations/0003_scene_alter_entity_description_alter_entity_switch_and_more.py
django_cad_inspector/migrations/0004_alter_entity_gltf_model_alter_entity_switch_and_more.py
django_cad_inspector/migrations/0005_alter_staging_color.py
django_cad_inspector/migrations/0006_staging_wireframe.py
django_cad_inspector/migrations/0007_alter_staging_position_alter_staging_rotation_and_more.py
django_cad_inspector/migrations/__init__.py
django_cad_inspector/templates/django_cad_inspector/admin_stagings.html
django_cad_inspector/templates/django_cad_inspector/base.html
django_cad_inspector/templates/django_cad_inspector/base_head.html
django_cad_inspector/templates/django_cad_inspector/entity_detail.html
django_cad_inspector/templates/django_cad_inspector/entity_list.html
django_cad_inspector/templates/django_cad_inspector/scene_detail.html
django_cad_inspector/templates/django_cad_inspector/scene_list.html
django_cad_inspector-0.6.0.dist-info/METADATA
django_cad_inspector-0.6.0.dist-info/WHEEL
django_cad_inspector-0.6.0.dist-info/licenses/LICENSE
django_cad_inspector-0.6.0.dist-info/RECORD
