Metadata-Version: 2.4
Name: django-cad-inspector
Version: 0.6.0
Summary: Import CAD drawings into Django and inspect them in VR with A-Frame
Project-URL: Repository, https://github.com/andywar65/django-cad-inspector
Author-email: andywar65 <andy.war1965@gmail.com>
License: MIT License
License-File: LICENSE
Classifier: Framework :: Django
Classifier: Operating System :: OS Independent
Classifier: Programming Language :: Python :: 3 :: Only
Classifier: Programming Language :: Python :: 3.9
Classifier: Programming Language :: Python :: 3.10
Classifier: Programming Language :: Python :: 3.11
Classifier: Programming Language :: Python :: 3.12
Classifier: Programming Language :: Python :: 3.13
Requires-Python: >=3.14
Requires-Dist: django-colorfield
Requires-Dist: django>=4.2
Requires-Dist: ezdxf
Requires-Dist: nh3
Requires-Dist: pillow
